{
    "category": "Experiment",
    "confidence": "High",
    "age_range": {
        "evidence": "The depressed group indicates users who received a total of at least 21 scores and then the non-depressed group is up to 20 scores. ... The males aged between 19 and 38 (Mean=25.61, SD=3.72) and the 51 (24%) were females aged between 19 and 33 (Mean=24.06, SD=2.69).",
        "value": [
            19,
            38
        ]
    },
    "fieldwork_year": {
        "evidence": "Participants were gathered over two periods of time, April and December in 2013",
        "value": 2013
    },
    "gender_split": {
        "evidence": "The males aged between 19 and 38 (Mean=25.61, SD=3.72) and the 51 (24%) were females aged between 19 and 33 (Mean=24.06, SD=2.69).",
        "value": {
            "male": 160,
            "female": 51,
            "other": 0
        }
    },
    "countries": {
        "evidence": "38,000 subjects from ten countries concluded that insomnia and lack of energy are the most common symptoms related to depression[52].",
        "value": []
    },
    "sample_size": {
        "evidence": "A total of 234 participants were recruited from a large university ... 212 (90%) completed the depression test",
        "value": 212
    }
}